autoencoder/__init__.py
autoencoder/model_parts.py
autoencoder/models.py
autoencoder-0.0.8.dist-info/LICENSE
autoencoder-0.0.8.dist-info/METADATA
autoencoder-0.0.8.dist-info/WHEEL
autoencoder-0.0.8.dist-info/top_level.txt
autoencoder-0.0.8.dist-info/RECORD
