Metadata-Version: 2.1
Name: autoencoder
Version: 0.0.8
Summary: A toolkit for flexibly building convolutional autoencoders in pytorch
Home-page: https://github.com/IljaManakov/ConvolutionalAutoencoderToolkit
Author: Ilja Manakov
Author-email: ilja.manakov@gmx.de
License: UNKNOWN
Platform: UNKNOWN
Classifier: Programming Language :: Python :: 3.6
Classifier: License :: OSI Approved :: MIT License
Classifier: Operating System :: OS Independent
